{
  "name": "交通手段",
  "description": "古代から現代まで、陸上から空中まで、人間の移動と貨物輸送の多様な方法を紹介し、技術と生活の進化を見守ります。",
  "groups": [
    {
      "name": "クラシックカー",
      "description": "古い車のレトロな優雅さとコレクション価値。"
    },
    {
      "name": "モダンカー",
      "description": "日常の通勤と家族の車の多様なデザイン。"
    },
    {
      "name": "列車と鉄道",
      "description": "長距離輸送、鉄道文化と駅の風景。"
    },
    {
      "name": "飛行機と空港",
      "description": "航空旅行と現代の飛行技術の象徴。"
    },
    {
      "name": "船と航海",
      "description": "遠洋貨物輸送またはクルーズ旅行の壮大な体験。"
    },
    {
      "name": "地下鉄とライトレール",
      "description": "都市の公共交通システムの便利な乗り物。"
    },
    {
      "name": "オートバイとバイクカルチャー",
      "description": "スピードと自由の象徴、街中を走るユニークな魅力。"
    },
    {
      "name": "熱気球",
      "description": "ゆっくりと上昇し、景色を一望するロマンチックな方法。"
    },
    {
      "name": "飛行船と空中交通",
      "description": "古典的でロマンチックな空中旅行機。"
    },
    {
      "name": "宇宙船と宇宙船",
      "description": "宇宙の探索と人類の夢の最先端技術。"
    },
    {
      "name": "クラシックホースカー",
      "description": "歴史時代の主要な交通手段の華麗さとレトロ。"
    },
    {
      "name": "マグレブトレイン",
      "description": "高速で低騒音の未来の列車技術。"
    },
    {
      "name": "宇宙エレベーター（サイファイ）",
      "description": "概念的な未来の輸送機関、地球と軌道を結ぶ。"
    },
    {
      "name": "未来のコンセプトカー",
      "description": "前衛的でハイテクな実験的な車。"
    },
    {
      "name": "潜水艇と水中航行",
      "description": "海底の秘密を探る特殊な乗り物。"
    },
    {
      "name": "貨物トラック",
      "description": "現代の物流と道路輸送の頼りになる後ろ盾。"
    },
    {
      "name": "豪華クルーズ",
      "description": "海上リゾートと観光を組み合わせた浮遊宮殿。"
    },
    {
      "name": "高速鉄道",
      "description": "都市と地域を超える高速旅客輸送システム。"
    },
    {
      "name": "レースカーとスーパーカー",
      "description": "究極の速度と車両工学の最高峰。"
    },
    {
      "name": "軍用車両",
      "description": "戦車、軍用機、装甲車などの軍事装備。"
    },
    {
      "name": "高所索道",
      "description": "谷や都市上空を跨ぐケーブルカー通路。"
    },
    {
      "name": "救助車両",
      "description": "消防車、救急車、警察車両などの緊急サービスツール。"
    },
    {
      "name": "自転車とサイクリング",
      "description": "緑の環境保護、健康的な移動の便利な方法。"
    },
    {
      "name": "自動運転車両",
      "description": "AI自動運転とスマートトラフィックの未来のトレンド。"
    }
  ]
}
