{
  "name": "自然の風景",
  "description": "高い山や氷河から海洋や湖まで、地球の豊かな生態系と地理的多様性を示す。",
  "groups": [
    {
      "name": "雪山",
      "description": "高地に位置し、雪と氷に覆われた山の頂上。"
    },
    {
      "name": "湖と滝",
      "description": "静かな湖面と流れる滝が調和した風景。"
    },
    {
      "name": "砂漠とゴビ",
      "description": "極めて乾燥した地域に広がる砂と荒涼とした風景。"
    },
    {
      "name": "森林の風景",
      "description": "高い木と密な植生が地球の自然の肺を形成。"
    },
    {
      "name": "海洋の世界",
      "description": "広大な海洋とその生物が青い生息地で活動。"
    },
    {
      "name": "夜明けと夕暮れ",
      "description": "夜明けと夕暮れに空が見せる壮大な変化。"
    },
    {
      "name": "熱帯雨林",
      "description": "湿潤で多様な植物と生物が生息する環境。"
    },
    {
      "name": "草原の風景",
      "description": "広大な草原と自由に草を食む牛や羊。"
    },
    {
      "name": "花畑と田園",
      "description": "カラフルな花と交錯する農地の風景。"
    },
    {
      "name": "丘陵と山地",
      "description": "緩やかな斜面と低山の豊かな植生。"
    },
    {
      "name": "島の海岸",
      "description": "海に囲まれた風光明媚な島々。"
    },
    {
      "name": "極光の風景",
      "description": "高緯度の空に現れるカラフルな光のショー。"
    },
    {
      "name": "火山地形",
      "description": "活発な火山とその地形。"
    },
    {
      "name": "岩石と奇妙な形",
      "description": "ユニークな岩石と奇妙な形状。"
    },
    {
      "name": "湿地と沼地",
      "description": "水と陸の境界に広がる多様な生態系。"
    },
    {
      "name": "極地の氷帽",
      "description": "極めて寒い地域を覆う巨大な氷の帽子。"
    },
    {
      "name": "峡谷と渓谷",
      "description": "川や風によって形成された深い谷。"
    },
    {
      "name": "高原の風景",
      "description": "広大で高い地域とその独特な気候。"
    },
    {
      "name": "カルスト地形",
      "description": "溶岩や鍾乳洞など、溶解性岩石のユニークな地形。"
    },
    {
      "name": "自然の風景",
      "description": "未開発で触れられていない自然の環境。"
    },
    {
      "name": "季節の風景",
      "description": "春夏秋冬の自然の変化。"
    },
    {
      "name": "虹の風景",
      "description": "空に現れる鮮やかで印象的な虹のショー。"
    },
    {
      "name": "地下洞窟",
      "description": "鍾乳石と地下河川が独特な空間を形成。"
    },
    {
      "name": "古木",
      "description": "長い年月を経た高い木。"
    }
  ]
}
